pyvideostream/__init__.py
pyvideostream/client.py
pyvideostream/server.py
pyvideostream-1.0.dist-info/METADATA
pyvideostream-1.0.dist-info/WHEEL
pyvideostream-1.0.dist-info/top_level.txt
pyvideostream-1.0.dist-info/RECORD
